{
  "entity.bogged.ambient": {
    "sounds": [
      "familiar_faces:bogged_ambient1",
      "familiar_faces:bogged_ambient2",
      "familiar_faces:bogged_ambient3",
      "familiar_faces:bogged_ambient4"
    ],
    "subtitle": "subtitles.entity.bogged.ambient"
  },
  "entity.bogged.death": {
    "sounds": [
      "familiar_faces:bogged_death"
    ],
    "subtitle": "subtitles.entity.bogged.death"
  },
  "entity.bogged.hurt": {
    "sounds": [
      "familiar_faces:bogged_hurt1",
      "familiar_faces:bogged_hurt2",
      "familiar_faces:bogged_hurt3",
      "familiar_faces:bogged_hurt4"
    ],
    "subtitle": "subtitles.entity.bogged.hurt"
  },
  "entity.bogged.step": {
    "sounds": [
      "familiar_faces:bogged_step1",
      "familiar_faces:bogged_step2",
      "familiar_faces:bogged_step3",
      "familiar_faces:bogged_step4"
    ],
    "subtitle": "subtitles.block.generic.footsteps"
  },
  "entity.breeze.charge": {
    "sounds": [
      "familiar_faces:breeze_charge1",
      "familiar_faces:breeze_charge2",
      "familiar_faces:breeze_charge3"
    ],
    "subtitle": "subtitles.entity.breeze.charge"
  },
  "entity.breeze.death": {
    "sounds": [
      "familiar_faces:breeze_death1",
      "familiar_faces:breeze_death2"
    ],
    "subtitle": "subtitles.entity.breeze.death"
  },
  "entity.breeze.deflect": {
    "sounds": [
      "familiar_faces:breeze_deflect1",
      "familiar_faces:breeze_deflect2",
      "familiar_faces:breeze_deflect3"
    ],
    "subtitle": "subtitles.entity.breeze.deflect"
  },
  "entity.breeze.hurt": {
    "sounds": [
      "familiar_faces:breeze_hurt1",
      "familiar_faces:breeze_hurt2",
      "familiar_faces:breeze_hurt3"
    ],
    "subtitle": "subtitles.entity.breeze.hurt"
  },
  "entity.breeze.idle_air": {
    "sounds": [
      "familiar_faces:breeze_idle_air1",
      "familiar_faces:breeze_idle_air2",
      "familiar_faces:breeze_idle_air3",
      "familiar_faces:breeze_idle_air4"
    ],
    "subtitle": "subtitles.entity.breeze.idle_air"
  },
  "entity.breeze.idle_ground": {
    "sounds": [
      "familiar_faces:breeze_idle1",
      "familiar_faces:breeze_idle2",
      "familiar_faces:breeze_idle3",
      "familiar_faces:breeze_idle4"
    ],
    "subtitle": "subtitles.entity.breeze.idle_ground"
  },
  "entity.breeze.inhale": {
    "sounds": [
      "familiar_faces:breeze_inhale1",
      {
        "name": "breeze_inhale1",
        "pitch": 1.1
      },
      "familiar_faces:breeze_inhale2",
      {
        "name": "breeze_inhale2",
        "pitch": 1.1
      }
    ],
    "subtitle": "subtitles.entity.breeze.inhale"
  },
  "entity.breeze.jump": {
    "sounds": [
      "familiar_faces:breeze_jump1",
      "familiar_faces:breeze_jump2"
    ],
    "subtitle": "subtitles.entity.breeze.jump"
  },
  "entity.breeze.land": {
    "sounds": [
      "familiar_faces:breeze_land1",
      "familiar_faces:breeze_land2"
    ],
    "subtitle": "subtitles.entity.breeze.land"
  },
  "entity.breeze.shoot": {
    "sounds": [
      "familiar_faces:breeze_shoot",
      {
        "name": "breeze_shoot",
        "pitch": 1.1
      },
      {
        "name": "breeze_shoot",
        "pitch": 1.2
      }
    ],
    "subtitle": "subtitles.entity.breeze.shoot"
  },
  "entity.breeze.slide": {
    "sounds": [
      "familiar_faces:breeze_slide1",
      "familiar_faces:breeze_slide3",
      "familiar_faces:breeze_slide2",
      "familiar_faces:breeze_slide4"
    ],
    "subtitle": "subtitles.entity.breeze.slide"
  },
  "entity.breeze.whirl": {
    "sounds": [
      "familiar_faces:breeze_whirl"
    ],
    "subtitle": "subtitles.entity.breeze.whirl"
  },
  "entity.breeze.wind_burst": {
    "sounds": [
      {
        "name": "wind_burst_1",
        "pitch": 1.2
      },
      {
        "name": "wind_burst_2",
        "pitch": 1.2
      },
      {
        "name": "wind_burst_3",
        "pitch": 1.2
      }
    ],
    "subtitle": "subtitles.entity.breeze.wind_burst"
  },
  "entity.wind_charge.throw": {
    "sounds": [
      "random/bow"
    ],
    "subtitle": "subtitles.entity.wind_charge.throw"
  },
  "entity.wind_charge.wind_burst": {
    "sounds": [
      {
        "attenuation_distance": 8,
        "name": "familiar_faces:wind_burst_1",
        "pitch": 1.25
      },
      {
        "name": "familiar_faces:wind_burst_2",
        "pitch": 1.25
      },
      {
        "name": "familiar_faces:wind_burst_3",
        "pitch": 1.25
      }
    ],
    "subtitle": "subtitles.entity.wind_charge.wind_burst"
  }
}